README.md
setup.py
mcush/AppUtils.py
mcush/Env.py
mcush/Instrument.py
mcush/Mcush.py
mcush/Modbus.py
mcush/Register.py
mcush/Utils.py
mcush/__init__.py
mcush.egg-info/PKG-INFO
mcush.egg-info/SOURCES.txt
mcush.egg-info/dependency_links.txt
mcush.egg-info/requires.txt
mcush.egg-info/top_level.txt
mcush/android/Kivy.py
mcush/android/Qpython.py
mcush/android/__init__.py
mcush/fluke/F5520A.py
mcush/fluke/F8808A.py
mcush/fluke/__init__.py
mcush/keysight/__init__.py
mcush/linkong/ShellKit.py
mcush/linkong/ShellLab.py
mcush/linkong/VAP.py
mcush/linkong/__init__.py
mcush/misc/Ads1115.py
mcush/misc/Aosong.py
mcush/misc/BeepPlayer.py
mcush/misc/Bh1750.py
mcush/misc/Bitmap.py
mcush/misc/Bosch.py
mcush/misc/Canvas.py
mcush/misc/Cs1238.py
mcush/misc/Dallas1W.py
mcush/misc/Feeltech.py
mcush/misc/Font.py
mcush/misc/GCode.py
mcush/misc/Gratten.py
mcush/misc/Hmc5883.py
mcush/misc/Hx711.py
mcush/misc/Ina219.py
mcush/misc/Korad.py
mcush/misc/Max30102.py
mcush/misc/Max31865.py
mcush/misc/Max6675.py
mcush/misc/Max7219.py
mcush/misc/Miaoguan.py
mcush/misc/Mlx90614.py
mcush/misc/MorseCodeBeeper.py
mcush/misc/Motion.py
mcush/misc/Omron.py
mcush/misc/OpenOCD.py
mcush/misc/Pca9685.py
mcush/misc/Sako.py
mcush/misc/SegmentTable.py
mcush/misc/Sensirion.py
mcush/misc/Ssd1306.py
mcush/misc/Tcs3472.py
mcush/misc/Tjc.py
mcush/misc/Tm1637.py
mcush/misc/Tm7707.py
mcush/misc/Tongmen.py
mcush/misc/WitMotion.py
mcush/misc/Ws2812.py
mcush/misc/Yaohua.py
mcush/misc/Zhouzheng.py
mcush/misc/__init__.py
mcush/rigol/DG1000Z.py
mcush/rigol/DG800.py
mcush/rigol/DM3058.py
mcush/rigol/DP700.py
mcush/rigol/DP800.py
mcush/rigol/DS1000.py
mcush/rigol/__init__.py
mcush/uni_trend/UT61.py
mcush/uni_trend/__init__.py