Metadata-Version: 2.1
Name: mcush
Version: 1.5.7
Summary: MCUSH project
Home-page: https://github.com/pengshulin/mcush/
Author: Peng Shulin
Author-email: trees_peng@163.com
License: MCUSH designed by Peng Shulin, all rights reserved.
Keywords: mcush shell embedded firmware test framework
Platform: UNKNOWN
Classifier: Development Status :: 3 - Alpha
Classifier: Intended Audience :: Developers
Classifier: Topic :: Software Development :: Build Tools
Classifier: License :: OSI Approved :: MIT License
Classifier: Programming Language :: Python :: 2
Classifier: Programming Language :: Python :: 2.7
Classifier: Programming Language :: Python :: 3
Classifier: Programming Language :: Python :: 3.3
Classifier: Programming Language :: Python :: 3.4
Classifier: Programming Language :: Python :: 3.5
Classifier: Programming Language :: Python :: 3.6
Classifier: Programming Language :: Python :: 3.7
Classifier: Programming Language :: Python :: 3.8
Provides-Extra: test
Provides-Extra: dev
